{"name":"build-javascript","namedChunkGroups":{"polyfill":{"name":"polyfill","assets":[{"name":"webpack-runtime-6e7d529196244c11a349.js","size":3603},{"name":"polyfill-87d69bc0fc06476cc09f.js","size":85011}],"filteredAssets":0,"assetsSize":88614,"filteredAuxiliaryAssets":2,"auxiliaryAssetsSize":225977},"app":{"name":"app","assets":[{"name":"webpack-runtime-6e7d529196244c11a349.js","size":3603},{"name":"framework-3475d84a0cc0db7d8ff3.js","size":140719},{"name":"app-df7c53bc0377abad627f.js","size":99775}],"filteredAssets":0,"assetsSize":244097,"filteredAuxiliaryAssets":3,"auxiliaryAssetsSize":810947},"component---src-pages-index-tsx":{"name":"component---src-pages-index-tsx","assets":[{"name":"component---src-pages-index-tsx-92caa7ea3bddc1bed459.js","size":271}],"filteredAssets":0,"assetsSize":271,"filteredAuxiliaryAssets":1,"auxiliaryAssetsSize":422}},"assetsByChunkName":{"polyfill":["webpack-runtime-6e7d529196244c11a349.js","polyfill-87d69bc0fc06476cc09f.js"],"app":["webpack-runtime-6e7d529196244c11a349.js","framework-3475d84a0cc0db7d8ff3.js","app-df7c53bc0377abad627f.js"],"component---src-pages-index-tsx":["component---src-pages-index-tsx-92caa7ea3bddc1bed459.js"]},"childAssetsByChunkName":{}}